RTL-Learning/modules/02_combinational/rtl/half_adder.v
module half_adder(
    input a,
    input b,
    output sum,
    output carry
);
    assign sum = a ^ b; // Sum is the XOR of inputs
    assign carry = a & b; // Carry is the AND of inputs

endmodule

RTL-Learning/modules/02_combinational/rtl/full_adder.v
module full_adder(
    input a,
    input b,
    input cin,
    output sum,
    output cout
);
    wire sum_half, carry_half1, carry_half2;

    // First half adder
    half_adder ha1 (
        .a(a),
        .b(b),
        .sum(sum_half),
        .carry(carry_half1)
    );

    // Second half adder
    half_adder ha2 (
        .a(sum_half),
        .b(cin),
        .sum(sum),
        .carry(carry_half2)
    );

    // Final carry out
    assign cout = carry_half1 | carry_half2;
endmodule

rtl2gds-project/modules/02_combinational/tb/full_tb.sv
`timescale 1ns/1ps

module full_adder_tb;
    reg a, b, cin;
    wire sum, cout;

    full_adder uut (
        .a(a),
        .b(b),
        .cin(cin),
        .sum(sum),
        .cout(cout)
    );

    initial begin
        $dumpfile("full_adder.vcd");
        $dumpvars(0, full_adder_tb);
        
        a = 0; b = 0; cin = 0; #10;
        a = 0; b = 1; cin = 0; #10;
        a = 1; b = 0; cin = 0; #10;
        a = 1; b = 1; cin = 0; #10;
        a = 0; b = 0; cin = 1; #10;
        a = 0; b = 1; cin = 1; #10;
        a = 1; b = 0; cin = 1; #10;
        a = 1; b = 1; cin = 1; #10;

        $finish;
    end
endmodule

rtl2gds-project/full_adder.vcd
$date
	Wed Jul 29 14:43:50 2026
$end
$version
	Icarus Verilog
$end
$timescale
	1ps
$end
$scope module full_adder_tb $end
$var wire 1 ! sum $end
$var wire 1 " cout $end
$var reg 1 # a $end
$var reg 1 $ b $end
$var reg 1 % cin $end
$scope module uut $end
$var wire 1 # a $end
$var wire 1 $ b $end
$var wire 1 % cin $end
$var wire 1 " cout $end
$var wire 1 & sum_half $end
$var wire 1 ! sum $end
$var wire 1 ' carry_half2 $end
$var wire 1 ( carry_half1 $end
$scope module ha1 $end
$var wire 1 # a $end
$var wire 1 $ b $end
$var wire 1 ( carry $end
$var wire 1 & sum $end
$upscope $end
$scope module ha2 $end
$var wire 1 & a $end
$var wire 1 % b $end
$var wire 1 ' carry $end
$var wire 1 ! sum $end
$upscope $end
$upscope $end
$upscope $end
$enddefinitions $end
$comment Show the parameter values. $end
$dumpall
$end
#0
$dumpvars
0(
0'
0&
0%
0$
0#
0"
0!
$end
#10000
1!
1&
1$
#20000
0$
1#
#30000
0!
1"
0&
1(
1$
#40000
0"
1!
0(
1%
0$
0#
#50000
1"
0!
1'
1&
1$
#60000
0$
1#
#70000
1!
0'
0&
1(
1$
