day02/COMB_ckt/mux_demux/rtl/2_x_1_mux.v
`timescale 1ns/1ps

module
    mux_2x1 (
        input wire A,
        input wire B,
        input wire sel,
        output wire Y
    );
    assign Y = sel ? B : A;
endmodule

day02/COMB_ckt/mux_demux/tb/mux2x1_tb.v
`timescale 1ns/1ps

module mux2x1_tb;
reg A;
reg B;
reg sel;
wire Y;

mux_2x1 dut(
    .A(A),
    .B(B),
    .sel(sel),
    .Y(Y)
);
initial begin
    $dumpfile("mux2x1.vcd");
    $dumpvars(0, mux2x1_tb);
    $display("2x1 MUX Truth table");
    $display("--------------------");
    $display("SEL A B | Y");
    $display("--------------------");
    sel=0; A=0; B=0; #10;
    $display("%b   %b %b | %b", sel, A, B, Y);
    sel=0; A=0; B=1; #10;
    $display("%b   %b %b | %b", sel, A, B, Y);
    sel=0; A=1; B=0; #10;
    $display("%b   %b %b | %b", sel, A, B, Y);
    sel=0; A=1; B=1; #10;
    $display("%b   %b %b | %b", sel, A, B, Y);
    sel=1; A=0; B=0; #10;
    $display("%b   %b %b | %b", sel, A, B, Y);
    sel=1; A=0; B=1; #10;
    $display("%b   %b %b | %b", sel, A, B, Y);
    sel=1; A=1; B=0; #10;
    $display("%b   %b %b | %b", sel, A, B, Y);
    sel=1; A=1; B=1; #10;
    $display("%b   %b %b | %b", sel, A, B, Y);
    $finish;
end

endmodule

day02/COMB_ckt/mux_demux/mux2x1.vcd
$date
	Fri Jul 10 05:26:01 2026
$end
$version
	Icarus Verilog
$end
$timescale
	1ps
$end
$scope module mux2x1_tb $end
$var wire 1 ! Y $end
$var reg 1 " A $end
$var reg 1 # B $end
$var reg 1 $ sel $end
$scope module dut $end
$var wire 1 " A $end
$var wire 1 # B $end
$var wire 1 $ sel $end
$var wire 1 ! Y $end
$upscope $end
$upscope $end
$enddefinitions $end
$comment Show the parameter values. $end
$dumpall
$end
#0
$dumpvars
0$
0#
0"
0!
$end
#10000
1#
#20000
1!
0#
1"
#30000
1#
#40000
0!
0#
0"
1$
#50000
1!
1#
#60000
0!
0#
1"
#70000
1!
1#
