day02/COMB_ckt/mux_demux/rtl/2_x_1_mux.v
`timescale 1ns/1ps

module
    mux_2x1 (
        input wire A,
        input wire B,
        input wire sel,
        output wire Y
    );
    assign Y = sel ? B : A;
endmodule

day02/COMB_ckt/mux_demux/rtl/4x1_mux.v
module mux_4x1(
        input wire A,
        input wire B,
        input wire C,
        input wire D,
        input wire sel0,
        input wire sel1,
        output wire Y
    );
    wire E;
    wire F;
    mux_2x1 u1(.A(A), .B(B), .sel(sel0), .Y(E));
    mux_2x1 u2(.A(C), .B(D), .sel(sel0), .Y(F));
    mux_2x1 u3(.A(E), .B(F), .sel(sel1), .Y(Y));
endmodule

day02/COMB_ckt/mux_demux/tb/mux4x1_tb.v
`timescale 1ns/1ps

module mux4x1_tb;

    reg A;
    reg B;
    reg C;
    reg D;
    reg sel0;
    reg sel1;
    wire Y;


    // Instantiate DUT
    mux_4x1 dut (
        .A(A),
        .B(B),
        .C(C),
        .D(D),
        .sel0(sel0),
        .sel1(sel1),
        .Y(Y)
    );

    initial begin

        // Generate waveform
        $dumpfile("sim/mux4x1.vcd");
        $dumpvars(0, mux4x1_tb);

        $display("-------------------------------------------");
        $display(" Time | S1 S0 | I0 I1 I2 I3 | Y");
        $display("-------------------------------------------");

        $monitor("%4t |  %b  %b |  %b  %b  %b  %b | %b",
                 $time, sel1, sel0, A, B, C, D, Y);

        // Test Case 1
        A = 0; B = 0; C = 0; D = 0;
        sel1 = 0; sel0 = 0;
        #10;

        // Test Case 2
        A = 1; B = 0; C = 0; D = 0;
        sel1 = 0; sel0 = 0;
        #10;

        // Test Case 3
        A = 0; B = 1; C = 0; D = 0;
        sel1 = 0; sel0 = 1;
        #10;

        // Test Case 4
        A = 0; B = 0; C = 1; D = 0;
        sel1 = 1; sel0 = 0;
        #10;

        // Test Case 5
        A = 0; B = 0; C = 0; D = 1;
        sel1 = 1; sel0 = 1;
        #10;

        // Test Case 6
        A = 1; B = 0; C = 1; D = 0;
        sel1 = 0; sel0 = 0;
        #10;

        // Test Case 7
        sel1 = 0; sel0 = 1;
        #10;

        // Test Case 8
        sel1 = 1; sel0 = 0;
        #10;

        // Test Case 9
        sel1 = 1; sel0 = 1;
        #10;

        $finish;

    end

endmodule

day02/COMB_ckt/mux_demux/sim/mux4x1.vcd
$date
	Fri Jul 10 06:03:57 2026
$end
$version
	Icarus Verilog
$end
$timescale
	1ps
$end
$scope module mux4x1_tb $end
$var wire 1 ! Y $end
$var reg 1 " A $end
$var reg 1 # B $end
$var reg 1 $ C $end
$var reg 1 % D $end
$var reg 1 & sel0 $end
$var reg 1 ' sel1 $end
$scope module dut $end
$var wire 1 " A $end
$var wire 1 # B $end
$var wire 1 $ C $end
$var wire 1 % D $end
$var wire 1 & sel0 $end
$var wire 1 ' sel1 $end
$var wire 1 ! Y $end
$var wire 1 ( F $end
$var wire 1 ) E $end
$scope module u1 $end
$var wire 1 " A $end
$var wire 1 # B $end
$var wire 1 & sel $end
$var wire 1 ) Y $end
$upscope $end
$scope module u2 $end
$var wire 1 $ A $end
$var wire 1 % B $end
$var wire 1 & sel $end
$var wire 1 ( Y $end
$upscope $end
$scope module u3 $end
$var wire 1 ) A $end
$var wire 1 ( B $end
$var wire 1 ' sel $end
$var wire 1 ! Y $end
$upscope $end
$upscope $end
$upscope $end
$enddefinitions $end
$comment Show the parameter values. $end
$dumpall
$end
#0
$dumpvars
0)
0(
0'
0&
0%
0$
0#
0"
0!
$end
#10000
1!
1)
1"
#20000
1&
1#
0"
#30000
1(
1!
0)
0&
1'
1$
0#
#40000
1&
1%
0$
#50000
1)
1!
0&
0'
0%
1$
1"
#60000
0!
0)
0(
1&
#70000
1!
1)
1(
0&
1'
#80000
0!
0)
0(
1&
